AUTHORS.rst
CONTRIBUTING.rst
LICENSE
MANIFEST.in
README.rst
requirements.txt
setup.cfg
setup.py
docs/Makefile
docs/make.bat
docs/source/conf.py
docs/source/index.rst
docs/source/installation.rst
docs/source/min_versions.rst
docs/source/release-history.rst
docs/source/usage.rst
finance_autofill/__init__.py
finance_autofill/main.py
finance_autofill.egg-info/PKG-INFO
finance_autofill.egg-info/SOURCES.txt
finance_autofill.egg-info/dependency_links.txt
finance_autofill.egg-info/entry_points.txt
finance_autofill.egg-info/requires.txt
finance_autofill.egg-info/top_level.txt
finance_autofill/tests/__init__.py
finance_autofill/tests/conftest.py
finance_autofill/tests/test_finance_autofill.py